odoo/addons/base_technical_features/README.rst
odoo/addons/base_technical_features/__init__.py
odoo/addons/base_technical_features/__manifest__.py
odoo/addons/base_technical_features/data/res_users.xml
odoo/addons/base_technical_features/i18n/am.po
odoo/addons/base_technical_features/i18n/ar.po
odoo/addons/base_technical_features/i18n/base_technical_features.pot
odoo/addons/base_technical_features/i18n/ca.po
odoo/addons/base_technical_features/i18n/da.po
odoo/addons/base_technical_features/i18n/de.po
odoo/addons/base_technical_features/i18n/el_GR.po
odoo/addons/base_technical_features/i18n/es.po
odoo/addons/base_technical_features/i18n/es_ES.po
odoo/addons/base_technical_features/i18n/es_MX.po
odoo/addons/base_technical_features/i18n/fi.po
odoo/addons/base_technical_features/i18n/fr.po
odoo/addons/base_technical_features/i18n/fr_CA.po
odoo/addons/base_technical_features/i18n/fr_CH.po
odoo/addons/base_technical_features/i18n/fr_FR.po
odoo/addons/base_technical_features/i18n/gl.po
odoo/addons/base_technical_features/i18n/hr.po
odoo/addons/base_technical_features/i18n/hr_HR.po
odoo/addons/base_technical_features/i18n/it.po
odoo/addons/base_technical_features/i18n/ja.po
odoo/addons/base_technical_features/i18n/nl.po
odoo/addons/base_technical_features/i18n/nl_NL.po
odoo/addons/base_technical_features/i18n/pt.po
odoo/addons/base_technical_features/i18n/pt_BR.po
odoo/addons/base_technical_features/i18n/pt_PT.po
odoo/addons/base_technical_features/i18n/ro.po
odoo/addons/base_technical_features/i18n/sl.po
odoo/addons/base_technical_features/i18n/tr.po
odoo/addons/base_technical_features/i18n/tr_TR.po
odoo/addons/base_technical_features/i18n/zh_CN.po
odoo/addons/base_technical_features/models/__init__.py
odoo/addons/base_technical_features/models/base.py
odoo/addons/base_technical_features/models/ir_ui_menu.py
odoo/addons/base_technical_features/models/res_users.py
odoo/addons/base_technical_features/readme/CONTRIBUTORS.rst
odoo13_addon_base_technical_features-13.0.1.0.1.dist-info/METADATA
odoo13_addon_base_technical_features-13.0.1.0.1.dist-info/WHEEL
odoo13_addon_base_technical_features-13.0.1.0.1.dist-info/top_level.txt
odoo13_addon_base_technical_features-13.0.1.0.1.dist-info/RECORD
